LICENSE
MANIFEST.in
README
setup.py
django_mailer/__init__.py
django_mailer/admin.py
django_mailer/constants.py
django_mailer/engine.py
django_mailer/lockfile.py
django_mailer/mail_utils.py
django_mailer/managers.py
django_mailer/models.py
django_mailer/settings.py
django_mailer/smtp_queue.py
django_mailer/management/__init__.py
django_mailer/management/commands/__init__.py
django_mailer/management/commands/cleanup_mail.py
django_mailer/management/commands/retry_deferred.py
django_mailer/management/commands/send_mail.py
django_mailer/management/commands/status_mail.py
django_mailer/templates/admin/django_mailer/message/change_form.html
django_mailer/templates/django_mailer/html_detail.html
django_mailer/templates/django_mailer/message_detail.html
django_mailer/templates/django_mailer/message_list.html
django_mailer_2.egg-info/PKG-INFO
django_mailer_2.egg-info/SOURCES.txt
django_mailer_2.egg-info/dependency_links.txt
django_mailer_2.egg-info/requires.txt
django_mailer_2.egg-info/top_level.txt
docs/Makefile
docs/conf.py
docs/index.rst
docs/install.rst
docs/settings.rst
docs/usage.rst