Metadata-Version: 1.1
Name: django-mailer-2
Version: 1.3.3
Summary: A reusable Django app for queueing the sending of email (forked aaloy on a frok from James Tauber's django-mailer)
Home-page: https://github.com/maykinmedia/django-mailer-2
Author: Antoni Aloy
Author-email: antoni.aloy@gmail.com
License: UNKNOWN
Platform: UNKNOWN
Classifier: Development Status :: 5 - Production/Stable
Classifier: Environment :: Web Environment
Classifier: Intended Audience :: Developers
Classifier: License :: OSI Approved :: MIT License
Classifier: Operating System :: OS Independent
Classifier: Programming Language :: Python
Classifier: Framework :: Django
